plover_svg_layout_display/__init__.py
plover_svg_layout_display/config_ui.py
plover_svg_layout_display/layout_config.py
plover_svg_layout_display/layout_ui.py
plover_svg_layout_display/qt_utils.py
plover_svg_layout_display/resources_rc.py
plover_svg_layout_display/svg_parser.py
plover_svg_layout_display/svg_widget.py
plover_svg_layout_display-1.0.0.dist-info/licenses/LICENSE.txt
plover_svg_layout_display-1.0.0.dist-info/METADATA
plover_svg_layout_display-1.0.0.dist-info/WHEEL
plover_svg_layout_display-1.0.0.dist-info/entry_points.txt
plover_svg_layout_display-1.0.0.dist-info/top_level.txt
plover_svg_layout_display-1.0.0.dist-info/zip-safe
plover_svg_layout_display-1.0.0.dist-info/RECORD
