Metadata-Version: 2.4
Name: plover-svg-layout-display
Version: 1.0.0
Summary: SVG-based layout display plugin for Plover
Home-page: https://github.com/Kaoffie/plover_svg_layout_display
Author: Kaoffie
Author-email: kaoffie@gmail.com
License: MIT License (MIT)
Keywords: plover plover_plugin
Classifier: Development Status :: 4 - Beta
Classifier: Environment :: Plugins
Classifier: Intended Audience :: End Users/Desktop
Classifier: License :: OSI Approved :: MIT License
Classifier: Operating System :: OS Independent
Classifier: Programming Language :: Python :: 3
Classifier: Programming Language :: Python :: 3.6
License-File: LICENSE.txt
Requires-Dist: plover>=5.0.0.dev3
Requires-Dist: lxml>=6.0.0
Dynamic: license-file
